[
    {
        "offer_id": "944645242",
        "title": "2 pokojowe mieszkanie z aneksem kuchennym i balkon",
        "price": "649 000 z\u0142",
        "location": "Wroc\u0142aw, Fabryczna",
        "date": "08 kwietnia 2025",
        "ref": "https://www.otodom.pl/pl/oferta/2-pokojowe-mieszkanie-z-aneksem-kuchennym-i-balkon-ID4spR6.html"
    },
    {
        "offer_id": "992052870",
        "title": "Nowe/ Okazja! Tylko umebluj i zamieszkaj!",
        "price": "515 889 z\u0142",
        "location": "Ole\u015bnica",
        "date": "27 marca 2025",
        "ref": "https://www.otodom.pl/pl/oferta/nowe-okazja-tylko-umebluj-i-zamieszkaj-ID4wER3.html"
    },
    {
        "offer_id": "967632532",
        "title": "Osiedle Re\u0144skie | mieszkanie 3-pok. | B_2",
        "price": "495 472 z\u0142",
        "location": "O\u0142awa",
        "date": "29 kwietnia 2025",
        "ref": "https://www.otodom.pl/pl/oferta/osiedle-renskie-mieszkanie-3-pok-b-2-ID4tGOZ.html"
    },
    {
        "offer_id": "1002148292",
        "title": "Armii Krajowej 8A - mieszkanie 2 pokoje - 73,03 m2",
        "price": "480 000 z\u0142",
        "location": "Brzeg",
        "date": "14 maja 2025",
        "ref": "https://www.otodom.pl/pl/oferta/armii-krajowej-8a-mieszkanie-2-pokoje-73-03-m2-ID4vnOo.html"
    },
    {
        "offer_id": "996653243",
        "title": "Przytulne 3 pokojowe mieszkanie 53m2 - Wojn\u00f3w",
        "price": "632 009 z\u0142",
        "location": "Wroc\u0142aw, Psie Pole",
        "date": "16 kwietnia 2025",
        "ref": "https://www.otodom.pl/pl/oferta/przytulne-3-pokojowe-mieszkanie-53m2-wojnow-ID4wZWF.html"
    },
    {
        "offer_id": "1000791421",
        "title": "Armii Krajowej | etap II | mieszkanie B.2.M1",
        "price": "748 356 z\u0142",
        "location": "Wroc\u0142aw, Krzyki",
        "date": "08 maja 2025",
        "ref": "https://www.otodom.pl/pl/oferta/armii-krajowej-etap-ii-mieszkanie-b-2-m1-ID4jFPA.html"
    },
    {
        "offer_id": "947082264",
        "title": "Promocja do ko\u0144ca maja 2025! Zielony Broch\u00f3w 7",
        "price": "560 222 z\u0142",
        "location": "Wroc\u0142aw, Krzyki",
        "date": "07 maja 2025",
        "ref": "https://www.otodom.pl/pl/oferta/promocja-do-konca-maja-2025-zielony-brochow-7-ID4sCYR.html"
    },
    {
        "offer_id": "883842045",
        "title": "70m\u00b2+OGR\u00d3D 61m\u00b2+1 m.parking+kom\u00f3rka-KAMERALNE",
        "price": "580 000 z\u0142",
        "location": "Lutynia",
        "date": "23 kwietnia 2025",
        "ref": "https://www.otodom.pl/pl/oferta/70m-ogrod-61m-1-m-parking-komorka-kameralne-ID4ofRF.html"
    },
    {
        "offer_id": "897437478",
        "title": "Zamieszkaj komfortowo",
        "price": "873 730 z\u0142",
        "location": "\u017bmigr\u00f3d",
        "date": "16 kwietnia 2025",
        "ref": "https://www.otodom.pl/pl/oferta/zamieszkaj-komfortowo-ID4p9UW.html"
    },
    {
        "offer_id": "1000113041",
        "title": "Lipa Piotrowska | mieszkanie C/K2/5",
        "price": "615 490 z\u0142",
        "location": "Wroc\u0142aw",
        "date": "05 maja 2025",
        "ref": "https://www.otodom.pl/pl/oferta/lipa-piotrowska-mieszkanie-c-k2-5-ID4so33.html"
    },
    {
        "offer_id": "765907508",
        "title": "Mieszkanie dwupoziomowe 121 m2 - gotowe z aktem",
        "price": "1 037 789,80 z\u0142",
        "location": "Wroc\u0142aw, Fabryczna",
        "date": "22 kwietnia 2025",
        "ref": "https://www.otodom.pl/pl/oferta/mieszkanie-dwupoziomowe-121-m2-gotowe-z-aktem-ID4ho3I.html"
    },
    {
        "offer_id": "982178706",
        "title": "2 pok,38m,MP,balkon",
        "price": "575 000 z\u0142",
        "location": "Wroc\u0142aw, Psie Pole",
        "date": "16 kwietnia 2025",
        "ref": "https://www.otodom.pl/pl/oferta/2-pok-38m-mp-balkon-ID4uYiC.html"
    },
    {
        "offer_id": "1000809530",
        "title": "Nowa Pabianicka - Wroc\u0142aw - Krzyki - Centrum",
        "price": "1 700 827 z\u0142",
        "location": "Wroc\u0142aw, Krzyki",
        "date": "08 maja 2025",
        "ref": "https://www.otodom.pl/pl/oferta/nowa-pabianicka-wroclaw-krzyki-centrum-ID4vig9.html"
    },
    {
        "offer_id": "850002831",
        "title": "GOTOWE 2-pokojowe mieszkanie 44m2 + balkon C2/P2/5",
        "price": "418 872 z\u0142",
        "location": "O\u0142awa",
        "date": "19 maja 2025",
        "ref": "https://www.otodom.pl/pl/oferta/gotowe-2-pokojowe-mieszkanie-44m2-balkon-c2-p2-5-ID4kShD.html"
    },
    {
        "offer_id": "995294441",
        "title": "Nowe mieszkanie przy ulicy Korczaka w Dzier\u017coniowie",
        "price": "420 000 z\u0142",
        "location": "Dzier\u017coni\u00f3w",
        "date": "dzisiaj o 15:42",
        "ref": "https://www.olx.pl/d/oferta/nowe-mieszkanie-przy-ulicy-korczaka-w-dzierzoniowie-CID3-ID15m9y9.html?reason=extended_search_extended_distance"
    },
    {
        "offer_id": "1000076576",
        "title": "Du\u017ce mieszkanie dla rodziny",
        "price": "850 000 z\u0142",
        "location": "Wroc\u0142aw, Fabryczna",
        "date": "05 maja 2025",
        "ref": "https://www.otodom.pl/pl/oferta/duze-mieszkanie-dla-rodziny-ID4v4tQ.html"
    },
    {
        "offer_id": "874254010",
        "title": "Pod Ole\u015bnic\u0105/Doskona\u0142e dla Rodziny/Dobra cena",
        "price": "378 386 z\u0142",
        "location": "Bierut\u00f3w",
        "date": "25 kwietnia 2025",
        "ref": "https://www.otodom.pl/pl/oferta/pod-olesnica-doskonale-dla-rodziny-dobra-cena-ID4nAyb.html"
    },
    {
        "offer_id": "997416245",
        "title": "Sprzedaz mieszkania",
        "price": "330 000 z\u0142",
        "location": "Grodk\u00f3w",
        "date": "21 kwietnia 2025",
        "ref": "https://www.olx.pl/d/oferta/sprzedaz-mieszkania-CID3-ID15w3vN.html?reason=extended_search_extended_distance"
    },
    {
        "offer_id": "999544609",
        "title": "A-1-2 59,49 m2, taras 43m2+balkon, wysoki standard",
        "price": "844 758 z\u0142",
        "location": "Wroc\u0142aw, Krzyki",
        "date": "02 maja 2025",
        "ref": "https://www.otodom.pl/pl/oferta/a-1-2-59-49-m2-taras-43m2-balkon-wysoki-standard-ID4wcyE.html"
    },
    {
        "offer_id": "1002533909",
        "title": "Mieszkanke 3 pokojowe w \u015arodzie \u015al\u0105skiej 62m2",
        "price": "569 000 z\u0142\ndo negocjacji",
        "location": "\u015aroda \u015al\u0105ska",
        "date": "15 maja 2025",
        "ref": "https://www.olx.pl/d/oferta/mieszkanke-3-pokojowe-w-srodzie-slaskiej-62m2-CID3-ID15QvRL.html?reason=extended_search_extended_distance"
    },
    {
        "offer_id": "923299871",
        "title": "Mieszkanie z antresol\u0105 GOTOWE DO ODBIORU! w Brzegu",
        "price": "659 464 z\u0142",
        "location": "Brzeg",
        "date": "30 kwietnia 2025",
        "ref": "https://www.otodom.pl/pl/oferta/mieszkanie-z-antresola-gotowe-do-odbioru-w-brzegu-ID4qV9q.html"
    },
    {
        "offer_id": "866709494",
        "title": "Przysta\u0144 Kr\u00f3lewiecka III | mieszkanie K2/26",
        "price": "810 870 z\u0142",
        "location": "Wroc\u0142aw, Fabryczna",
        "date": "25 kwietnia 2025",
        "ref": "https://www.otodom.pl/pl/oferta/przystan-krolewiecka-iii-mieszkanie-k2-26-ID4kGjy.html"
    },
    {
        "offer_id": "998621714",
        "title": "Mieszkanie B4M9 o powierzchni 50 m2",
        "price": "398 400 z\u0142",
        "location": "Brzeg",
        "date": "27 kwietnia 2025",
        "ref": "https://www.otodom.pl/pl/oferta/mieszkanie-b4m9-o-powierzchni-50-m2-ID4wEDj.html"
    },
    {
        "offer_id": "992262892",
        "title": "Mieszkanie wyko\u0144czone pod klucz - PARK VERDE",
        "price": "450 810 z\u0142",
        "location": "Brzeg",
        "date": "07 maja 2025",
        "ref": "https://www.otodom.pl/pl/oferta/mieszkanie-wykonczone-pod-klucz-park-verde-ID4wEPQ.html"
    },
    {
        "offer_id": "1000358744",
        "title": "APARTAMENT \u2b50 Odlicz VAT 23% \u2b50 Zostaw wiadomo\u015b\u0107!",
        "price": "406 458 z\u0142",
        "location": "Wroc\u0142aw, Fabryczna",
        "date": "06 maja 2025",
        "ref": "https://www.otodom.pl/pl/oferta/apartament-odlicz-vat-23-zostaw-wiadomosc-ID4vfKi.html"
    },
    {
        "offer_id": "1001117268",
        "title": "Armii Krajowej 8A - mieszkanie 2 pokoje - 39,88 m2",
        "price": "278 900 z\u0142",
        "location": "Brzeg",
        "date": "09 maja 2025",
        "ref": "https://www.otodom.pl/pl/oferta/armii-krajowej-8a-mieszkanie-2-pokoje-39-88-m2-ID4vjMs.html"
    },
    {
        "offer_id": "1000791452",
        "title": "Stalova | mieszkanie 2-pok. | 6.K2.5",
        "price": "744 120 z\u0142",
        "location": "Wroc\u0142aw, Fabryczna",
        "date": "08 maja 2025",
        "ref": "https://www.otodom.pl/pl/oferta/stalova-mieszkanie-2-pok-6-k2-5-ID4mxtO.html"
    },
    {
        "offer_id": "1001435384",
        "title": "Budowa zako\u0144czona, Standard premium, Winda!",
        "price": "699 000 z\u0142",
        "location": "Wroc\u0142aw, Fabryczna",
        "date": "11 maja 2025",
        "ref": "https://www.otodom.pl/pl/oferta/budowa-zakonczona-standard-premium-winda-ID4vgyH.html"
    },
    {
        "offer_id": "889751832",
        "title": "Ostatnie mieszkanie! \u017beromskiego 51!",
        "price": "842 010 z\u0142",
        "location": "Wroc\u0142aw, \u015ar\u00f3dmie\u015bcie",
        "date": "12 maja 2025",
        "ref": "https://www.otodom.pl/pl/oferta/ostatnie-mieszkanie-zeromskiego-51-ID4oCxo.html"
    },
    {
        "offer_id": "1001967204",
        "title": "\u017begiestowska | mieszkanie 1-pok. | 3.M.07",
        "price": "377 848 z\u0142",
        "location": "Wroc\u0142aw, Krzyki",
        "date": "13 maja 2025",
        "ref": "https://www.otodom.pl/pl/oferta/zegiestowska-mieszkanie-1-pok-3-m-07-ID4qDJ4.html"
    },
    {
        "offer_id": "998364233",
        "title": "Armii Krajowej 8A - mieszkanie 2 pokoje - 41,63 m2",
        "price": "291 300 z\u0142",
        "location": "Brzeg",
        "date": "25 kwietnia 2025",
        "ref": "https://www.otodom.pl/pl/oferta/armii-krajowej-8a-mieszkanie-2-pokoje-41-63-m2-ID4v7JA.html"
    },
    {
        "offer_id": "1003458658",
        "title": "OKAZJA! Mieszkanie 4-pokojowe z 2 \u0142azienkami",
        "price": "641 690 z\u0142",
        "location": "Wroc\u0142aw, Krzyki",
        "date": "dzisiaj o 15:15",
        "ref": "https://www.olx.pl/d/oferta/okazja-mieszkanie-4-pokojowe-z-2-lazienkami-CID3-ID15Upr4.html"
    },
    {
        "offer_id": "943650898",
        "title": "Nowe! 2-pokoje + taras! Elegancka inwestycja! - RADWANICE",
        "price": "472 200 z\u0142",
        "location": "Wroc\u0142aw, Krzyki",
        "date": "25 kwietnia 2025",
        "ref": "https://www.olx.pl/d/oferta/nowe-2-pokoje-taras-elegancka-inwestycja-radwanice-CID3-ID11RsHM.html"
    },
    {
        "offer_id": "996646244",
        "title": "Mieszkanie dla Inwestora \"3 w 1\"",
        "price": "1 318 977 z\u0142",
        "location": "Wroc\u0142aw, Psie Pole",
        "date": "16 kwietnia 2025",
        "ref": "https://www.otodom.pl/pl/oferta/mieszkanie-dla-inwestora-3-w-1-ID4wZRY.html"
    },
    {
        "offer_id": "1000819016",
        "title": "Apartamenty przy Parku Szczytnickim | 4-pok mieszkanie z ogr\u00f3dkiem",
        "price": "2 138 918,20 z\u0142",
        "location": "Wroc\u0142aw, \u015ar\u00f3dmie\u015bcie",
        "date": "08 maja 2025",
        "ref": "https://www.otodom.pl/pl/oferta/apartamenty-przy-parku-szczytnickim-4-pok-mieszkanie-z-ogrodkiem-ID4vilI.html"
    },
    {
        "offer_id": "990654846",
        "title": "2 pokoje/W\u015br\u00f3d zieleni",
        "price": "540 000 z\u0142",
        "location": "Wroc\u0142aw, Krzyki",
        "date": "22 marca 2025",
        "ref": "https://www.otodom.pl/pl/oferta/2-pokoje-wsrod-zieleni-ID4wvC3.html"
    },
    {
        "offer_id": "1001209544",
        "title": "Piastowska 54",
        "price": "303 810 z\u0142",
        "location": "Brzeg",
        "date": "10 maja 2025",
        "ref": "https://www.otodom.pl/pl/oferta/piastowska-54-ID4wTLi.html"
    },
    {
        "offer_id": "781563330",
        "title": "Nowe bloki, Korczaka 15 B, parter",
        "price": "419 930 z\u0142",
        "location": "Dzier\u017coni\u00f3w",
        "date": "28 kwietnia 2025",
        "ref": "https://www.otodom.pl/pl/oferta/nowe-bloki-korczaka-15-b-parter-ID4iqTu.html"
    },
    {
        "offer_id": "761293378",
        "title": "111m\u00b2+BALKON+1 m.parking.+kom\u00f3rka-KAMERALNE-C",
        "price": "580 000 z\u0142",
        "location": "Lutynia",
        "date": "23 kwietnia 2025",
        "ref": "https://www.otodom.pl/pl/oferta/111m-balkon-1-m-parking-komorka-kameralne-c-ID4h4qR.html"
    },
    {
        "offer_id": "882108612",
        "title": "70m\u00b2+ OGR\u00d3D 150m\u00b2 +m.postojowe -KAMERALNE-C",
        "price": "640 000 z\u0142",
        "location": "Lutynia",
        "date": "23 kwietnia 2025",
        "ref": "https://www.otodom.pl/pl/oferta/70m-ogrod-150m-m-postojowe-kameralne-c-ID4oa1Z.html"
    },
    {
        "offer_id": "895755412",
        "title": "Dobre na start / Inwestycje / S\u0142oneczne / Ciche",
        "price": "514 300 z\u0142",
        "location": "Wroc\u0142aw, Psie Pole",
        "date": "08 maja 2025",
        "ref": "https://www.otodom.pl/pl/oferta/dobre-na-start-inwestycje-sloneczne-ciche-ID4oZlp.html"
    },
    {
        "offer_id": "983567570",
        "title": "Nowy Apartament Blok LUX Klima 3 pok",
        "price": "725 000 z\u0142",
        "location": "Ole\u015bnica",
        "date": "23 marca 2025",
        "ref": "https://www.otodom.pl/pl/oferta/nowy-apartament-blok-lux-klima-3-pok-ID4w3Hn.html"
    },
    {
        "offer_id": "999927495",
        "title": "Browary Brzeskie | NOWE mieszkanie 61,99 m2",
        "price": "557 910 z\u0142",
        "location": "Brzeg",
        "date": "04 maja 2025",
        "ref": "https://www.otodom.pl/pl/oferta/browary-brzeskie-nowe-mieszkanie-61-99-m2-ID4elEf.html"
    },
    {
        "offer_id": "996649997",
        "title": "Komfortowe mieszkanie 70m2 w spokojnej okolicy!",
        "price": "784 190 z\u0142",
        "location": "Wroc\u0142aw",
        "date": "16 kwietnia 2025",
        "ref": "https://www.otodom.pl/pl/oferta/komfortowe-mieszkanie-70m2-w-spokojnej-okolicy-ID4wZUr.html"
    },
    {
        "offer_id": "948746121",
        "title": "Osiedle Ko\u015bciuszki Brzeg --\" najlepsza lokalizacja w Brzegu \" --",
        "price": "323 400 z\u0142",
        "location": "Brzeg",
        "date": "08 maja 2025",
        "ref": "https://www.otodom.pl/pl/oferta/osiedle-kosciuszki-brzeg-najlepsza-lokalizacja-w-brzegu-ID4sJwE.html"
    },
    {
        "offer_id": "996665373",
        "title": "2 pokoje, 45m2 z widokiem na park - cisza i ziele\u0144",
        "price": "605 200 z\u0142",
        "location": "Wroc\u0142aw",
        "date": "16 kwietnia 2025",
        "ref": "https://www.otodom.pl/pl/oferta/2-pokoje-45m2-z-widokiem-na-park-cisza-i-zielen-ID4v00k.html"
    },
    {
        "offer_id": "967824279",
        "title": "Nowe bloki, Korczaka 15 C, parter, ogr\u00f3dek,balkony",
        "price": "470 376 z\u0142",
        "location": "Dzier\u017coni\u00f3w",
        "date": "28 kwietnia 2025",
        "ref": "https://www.otodom.pl/pl/oferta/nowe-bloki-korczaka-15-c-parter-ogrodek-balkony-ID4tUzy.html"
    },
    {
        "offer_id": "992262964",
        "title": "VERDE PARK Mieszkanie wyko\u0144czone pod klucz",
        "price": "520 200 z\u0142",
        "location": "Brzeg",
        "date": "28 marca 2025",
        "ref": "https://www.otodom.pl/pl/oferta/verde-park-mieszkanie-wykonczone-pod-klucz-ID4wETi.html"
    },
    {
        "offer_id": "1000806555",
        "title": "Nowa Pabianicka - Wroc\u0142aw - Krzyki - Centrum",
        "price": "669 600 z\u0142",
        "location": "Wroc\u0142aw, Krzyki",
        "date": "08 maja 2025",
        "ref": "https://www.otodom.pl/pl/oferta/nowa-pabianicka-wroclaw-krzyki-centrum-ID4vie6.html"
    },
    {
        "offer_id": "998166503",
        "title": "Nowe mieszkanie + kom\u00f3rka lokatorska + 3 miejsca parkingowe + ogr\u00f3dek",
        "price": "740 000 z\u0142",
        "location": "Wroc\u0142aw, Krzyki",
        "date": "24 kwietnia 2025",
        "ref": "https://www.otodom.pl/pl/oferta/nowe-mieszkanie-komorka-lokatorska-3-miejsca-parkingowe-ogrodek-ID4v6BL.html"
    },
    {
        "offer_id": "761292473",
        "title": "70m\u00b2+OGR\u00d3D 61m\u00b2+1 m.parking+kom\u00f3rka-KAMERALNE-C",
        "price": "580 000 z\u0142",
        "location": "Lutynia",
        "date": "23 kwietnia 2025",
        "ref": "https://www.otodom.pl/pl/oferta/70m-ogrod-61m-1-m-parking-komorka-kameralne-c-ID4h4qy.html"
    },
    {
        "offer_id": "882109608",
        "title": "70m\u00b2+OGR\u00d3D 61m\u00b2+m.postojowe -KAMERALNE-C",
        "price": "580 000 z\u0142",
        "location": "Lutynia",
        "date": "25 kwietnia 2025",
        "ref": "https://www.otodom.pl/pl/oferta/70m-ogrod-61m-m-postojowe-kameralne-c-ID4o9WO.html"
    },
    {
        "offer_id": "998889356",
        "title": "DU\u017bY OGR\u00d3D \u2705 Wyko\u0144czenie w cenie \u2705 Inwestycyjnie!",
        "price": "448 332 z\u0142",
        "location": "Wroc\u0142aw, Fabryczna",
        "date": "28 kwietnia 2025",
        "ref": "https://www.otodom.pl/pl/oferta/duzy-ogrod-wykonczenie-w-cenie-inwestycyjnie-ID4v9qG.html"
    },
    {
        "offer_id": "999570617",
        "title": "4 pokoje|Zielona okolica|Tramwaj|",
        "price": "894 925 z\u0142",
        "location": "Wroc\u0142aw",
        "date": "02 maja 2025",
        "ref": "https://www.otodom.pl/pl/oferta/4-pokoje-zielona-okolica-tramwaj-ID4tmnY.html"
    },
    {
        "offer_id": "1000743096",
        "title": "Mieszkanie na sprzeda\u017c 54,70m2",
        "price": "514 180 z\u0142",
        "location": "Jelcz",
        "date": "laskowice",
        "ref": "https://www.otodom.pl/pl/oferta/mieszkanie-na-sprzedaz-54-70m2-ID4n4Sg.html"
    },
    {
        "offer_id": "883843605",
        "title": "70m\u00b2+OGR\u00d3D 61m\u00b2+1 m.parking+kom\u00f3rka-KAMERALNE",
        "price": "580 000 z\u0142",
        "location": "Lutynia",
        "date": "23 kwietnia 2025",
        "ref": "https://www.otodom.pl/pl/oferta/70m-ogrod-61m-1-m-parking-komorka-kameralne-ID4ofPg.html"
    },
    {
        "offer_id": "969235124",
        "title": "15 minut od Ole\u015bnicy/dobra cena!",
        "price": "364 973 z\u0142",
        "location": "Bierut\u00f3w",
        "date": "25 kwietnia 2025",
        "ref": "https://www.otodom.pl/pl/oferta/15-minut-od-olesnicy-dobra-cena-ID4tVGx.html"
    },
    {
        "offer_id": "1000242829",
        "title": "Dwu poziomowe mieszkanie w nowym bloku , dobra cena !",
        "price": "1 190 000 z\u0142",
        "location": "Wroc\u0142aw, Psie Pole",
        "date": "05 maja 2025",
        "ref": "https://www.olx.pl/d/oferta/dwu-poziomowe-mieszkanie-w-nowym-bloku-dobra-cena-CID3-ID15GUQR.html"
    },
    {
        "offer_id": "906594515",
        "title": "Nowoczesne mieszkanie na sprzeda\u017c",
        "price": "899 000 z\u0142",
        "location": "Trzebnica",
        "date": "25 marca 2025",
        "ref": "https://www.otodom.pl/pl/oferta/nowoczesne-mieszkanie-na-sprzedaz-ID4pMap.html"
    },
    {
        "offer_id": "992875123",
        "title": "MIESZKANIE 3 pokojowe ul. Rymarska-Rac\u0142awicka",
        "price": "950 000 z\u0142",
        "location": "Wroc\u0142aw, Krzyki",
        "date": "30 marca 2025",
        "ref": "https://www.otodom.pl/pl/oferta/mieszkanie-3-pokojowe-ul-rymarska-raclawicka-ID4lrBc.html"
    },
    {
        "offer_id": "882108740",
        "title": "111m\u00b2+BALKONON+m.parkingowe+kom\u00f3rka-KAMERALNE C",
        "price": "580 000 z\u0142",
        "location": "Lutynia",
        "date": "23 kwietnia 2025",
        "ref": "https://www.otodom.pl/pl/oferta/111m-balkonon-m-parkingowe-komorka-kameralne-c-ID4oa12.html"
    },
    {
        "offer_id": "1003035954",
        "title": "Kopernika 16 | mieszkanie 3-pok. | F03",
        "price": "674 956 z\u0142",
        "location": "Ole\u015bnica",
        "date": "18 maja 2025",
        "ref": "https://www.otodom.pl/pl/oferta/kopernika-16-mieszkanie-3-pok-f03-ID4vbrU.html"
    },
    {
        "offer_id": "986518647",
        "title": "Rodzinny uk\u0142ad \u2022 Zielona okolica \u2022 Wysoki sufit",
        "price": "787 913 z\u0142",
        "location": "Wroc\u0142aw, Krzyki",
        "date": "dzisiaj o 16:48",
        "ref": "https://www.otodom.pl/pl/oferta/rodzinny-uklad-zielona-okolica-wysoki-sufit-ID4wgn3.html"
    },
    {
        "offer_id": "990036115",
        "title": "Nowa, energooszcz\u0119dna kawalerka w Inwestycji LE\u015aNA 7",
        "price": "317 088 z\u0142",
        "location": "Strzelin",
        "date": "20 kwietnia 2025",
        "ref": "https://www.olx.pl/d/oferta/nowa-energooszczedna-kawalerka-w-inwestycji-lesna-7-CID3-ID1505Cr.html?reason=extended_search_extended_distance"
    },
    {
        "offer_id": "946964457",
        "title": "Mieszkanie Grodk\u00f3w",
        "price": "355 000 z\u0142",
        "location": "Grodk\u00f3w",
        "date": "od\u015bwie\u017cono dnia 16 maja 2025",
        "ref": "https://www.olx.pl/d/oferta/mieszkanie-grodkow-CID3-ID125mIh.html?reason=extended_search_extended_distance"
    },
    {
        "offer_id": "990198533",
        "title": "Mieszkanie Z Ogrodem | Sady Nad Zielon\u0105",
        "price": "565 275 z\u0142",
        "location": "Wroc\u0142aw, Krzyki",
        "date": "26 kwietnia 2025",
        "ref": "https://www.otodom.pl/pl/oferta/mieszkanie-z-ogrodem-sady-nad-zielona-ID4wrGn.html"
    },
    {
        "offer_id": "884664059",
        "title": "70m\u00b2+OGR\u00d3D 61m\u00b2+1 m.parking+kom\u00f3rka-KAMERALNE",
        "price": "580 000 z\u0142",
        "location": "Lutynia",
        "date": "23 kwietnia 2025",
        "ref": "https://www.otodom.pl/pl/oferta/70m-ogrod-61m-1-m-parking-komorka-kameralne-ID4ofMZ.html"
    },
    {
        "offer_id": "973223324",
        "title": "2 pokoje / blisko park / spokojna okolica",
        "price": "372 200 z\u0142",
        "location": "Wroc\u0142aw, Krzyki",
        "date": "27 kwietnia 2025",
        "ref": "https://www.otodom.pl/pl/oferta/2-pokoje-blisko-park-spokojna-okolica-ID4uef5.html"
    },
    {
        "offer_id": "967632522",
        "title": "Osiedle Re\u0144skie | mieszkanie 4-pok. | B_7",
        "price": "602 532 z\u0142",
        "location": "O\u0142awa",
        "date": "29 kwietnia 2025",
        "ref": "https://www.otodom.pl/pl/oferta/osiedle-renskie-mieszkanie-4-pok-b-7-ID4tGP0.html"
    },
    {
        "offer_id": "918965417",
        "title": "Naro\u017cne jasne mieszkanie z widokiem na \u015al\u0119\u017c\u0119",
        "price": "399 000 z\u0142",
        "location": "\u015awidnica",
        "date": "31 marca 2025",
        "ref": "https://www.otodom.pl/pl/oferta/narozne-jasne-mieszkanie-z-widokiem-na-sleze-ID4qD47.html"
    },
    {
        "offer_id": "1003035945",
        "title": "Kopernika 16 | mieszkanie 2-pok. | D05",
        "price": "507 590 z\u0142",
        "location": "Ole\u015bnica",
        "date": "18 maja 2025",
        "ref": "https://www.otodom.pl/pl/oferta/kopernika-16-mieszkanie-2-pok-d05-ID4vbrO.html"
    },
    {
        "offer_id": "1000799923",
        "title": "Gotowe | Ciekawy uk\u0142ad | Garderoba | Du\u017ce Rabaty",
        "price": "669 000 z\u0142",
        "location": "Wroc\u0142aw, Psie Pole",
        "date": "08 maja 2025",
        "ref": "https://www.otodom.pl/pl/oferta/gotowe-ciekawy-uklad-garderoba-duze-rabaty-ID4uPXB.html"
    },
    {
        "offer_id": "991568115",
        "title": "2 pokoje / 1 pi\u0119tro / winda / balkon / parking",
        "price": "449 900 z\u0142",
        "location": "Brzeg Dolny",
        "date": "27 kwietnia 2025",
        "ref": "https://www.otodom.pl/pl/oferta/2-pokoje-1-pietro-winda-balkon-parking-ID4wCfC.html"
    },
    {
        "offer_id": "761291482",
        "title": "70m\u00b2 +ogr\u00f3dek+1m.parkingowe+kom\u00f3rka-KAMERALNE-C",
        "price": "580 000 z\u0142",
        "location": "Lutynia",
        "date": "25 kwietnia 2025",
        "ref": "https://www.otodom.pl/pl/oferta/70m-ogrodek-1m-parkingowe-komorka-kameralne-c-ID4h4qf.html"
    },
    {
        "offer_id": "970827533",
        "title": "Sprzedam mieszkanie 28,08m2 w centrum miasta",
        "price": "515 000 z\u0142",
        "location": "Wroc\u0142aw, Stare Miasto",
        "date": "23 kwietnia 2025",
        "ref": "https://www.otodom.pl/pl/oferta/sprzedam-mieszkanie-28-08m2-w-centrum-miasta-ID4u3O6.html"
    },
    {
        "offer_id": "1003035955",
        "title": "Kopernika 16 | mieszkanie 2-pok. | E05",
        "price": "500 011 z\u0142",
        "location": "Ole\u015bnica",
        "date": "18 maja 2025",
        "ref": "https://www.otodom.pl/pl/oferta/kopernika-16-mieszkanie-2-pok-e05-ID4vbrR.html"
    },
    {
        "offer_id": "883841938",
        "title": "70m\u00b2+OGR\u00d3D 61m\u00b2+1 m.parking+kom\u00f3rka-KAMERALNE",
        "price": "580 000 z\u0142",
        "location": "Lutynia",
        "date": "23 kwietnia 2025",
        "ref": "https://www.otodom.pl/pl/oferta/70m-ogrod-61m-1-m-parking-komorka-kameralne-ID4ofSe.html"
    },
    {
        "offer_id": "761290178",
        "title": "70 m\u00b2+OGR\u00d3DEK +1miejsce parking.-KAMERALNE - C",
        "price": "580 000 z\u0142",
        "location": "Lutynia",
        "date": "25 kwietnia 2025",
        "ref": "https://www.otodom.pl/pl/oferta/70-m-ogrodek-1miejsce-parking-kameralne-c-ID4h4pN.html"
    },
    {
        "offer_id": "993719209",
        "title": "\u017bmigr\u00f3d- nowe mieszkanie",
        "price": "521 370 z\u0142",
        "location": "\u017bmigr\u00f3d",
        "date": "03 kwietnia 2025",
        "ref": "https://www.otodom.pl/pl/oferta/zmigrod-nowe-mieszkanie-ID4wMr1.html"
    },
    {
        "offer_id": "943667554",
        "title": "LUKSUSOWY 3-pokojowy apartament z du\u017cym TARASEM!",
        "price": "605 000 z\u0142",
        "location": "Wroc\u0142aw, Krzyki",
        "date": "29 kwietnia 2025",
        "ref": "https://www.olx.pl/d/oferta/luksusowy-3-pokojowy-apartament-z-duzym-tarasem-CID3-ID11Rx2q.html"
    },
    {
        "offer_id": "995006347",
        "title": "Wroc\u0142aw: 2 kawalerki premium z ogr\u00f3dkiem - VAT 23%",
        "price": "429 990 z\u0142",
        "location": "Wroc\u0142aw, Krzyki",
        "date": "08 kwietnia 2025",
        "ref": "https://www.otodom.pl/pl/oferta/wroclaw-2-kawalerki-premium-z-ogrodkiem-vat-23-ID4wRC7.html"
    },
    {
        "offer_id": "1002021556",
        "title": "GOTOWE 2-pokojowe mieszkanie 43,49 m2 | D2/P4/1",
        "price": "404 457 z\u0142",
        "location": "O\u0142awa",
        "date": "13 maja 2025",
        "ref": "https://www.otodom.pl/pl/oferta/gotowe-2-pokojowe-mieszkanie-43-49-m2-d2-p4-1-ID4rUEX.html"
    },
    {
        "offer_id": "1000230284",
        "title": "Mieszkanie 63m2 w nowym bloku. Okazja",
        "price": "900 000 z\u0142",
        "location": "Wroc\u0142aw, Psie Pole",
        "date": "05 maja 2025",
        "ref": "https://www.olx.pl/d/oferta/mieszkanie-63m2-w-nowym-bloku-okazja-CID3-ID15GRAv.html"
    },
    {
        "offer_id": "847741637",
        "title": "NOWE BLOKI Korczaka 15 D ,3 pokoje, II pi\u0119tro",
        "price": "521 597 z\u0142",
        "location": "Dzier\u017coni\u00f3w",
        "date": "12 maja 2025",
        "ref": "https://www.otodom.pl/pl/oferta/nowe-bloki-korczaka-15-d-3-pokoje-ii-pietro-ID4meUf.html"
    },
    {
        "offer_id": "852928195",
        "title": "Przysta\u0144 Kr\u00f3lewiecka III | mieszkanie K2/23",
        "price": "768 642 z\u0142",
        "location": "Wroc\u0142aw, Fabryczna",
        "date": "25 kwietnia 2025",
        "ref": "https://www.otodom.pl/pl/oferta/przystan-krolewiecka-iii-mieszkanie-k2-23-ID4kGjL.html"
    },
    {
        "offer_id": "951305961",
        "title": "Nowe mieszkanie ze s\u0142oneczn\u0105 sypialni\u0105 w Inwestycji LE\u015aNA 7",
        "price": "365 050 z\u0142",
        "location": "Strzelin",
        "date": "20 kwietnia 2025",
        "ref": "https://www.olx.pl/d/oferta/nowe-mieszkanie-ze-sloneczna-sypialnia-w-inwestycji-lesna-7-CID3-ID12nA8x.html?reason=extended_search_extended_distance"
    },
    {
        "offer_id": "1002730822",
        "title": "Armii Krajowej 8A - mieszkanie 2 pokoje - 41,69 m2",
        "price": "291 500 z\u0142",
        "location": "Brzeg",
        "date": "16 maja 2025",
        "ref": "https://www.otodom.pl/pl/oferta/armii-krajowej-8a-mieszkanie-2-pokoje-41-69-m2-ID4vqjS.html"
    },
    {
        "offer_id": "884663817",
        "title": "111m\u00b2-2 poziomy+balkon+m.parking-KAMERALNE",
        "price": "580 000 z\u0142",
        "location": "Lutynia",
        "date": "23 kwietnia 2025",
        "ref": "https://www.otodom.pl/pl/oferta/111m-2-poziomy-balkon-m-parking-kameralne-ID4ofNP.html"
    },
    {
        "offer_id": "883843522",
        "title": "111m\u00b2-2 poziomy+balkon+ m.parking-KAMERALNE",
        "price": "580 000 z\u0142",
        "location": "Lutynia",
        "date": "23 kwietnia 2025",
        "ref": "https://www.otodom.pl/pl/oferta/111m-2-poziomy-balkon-m-parking-kameralne-ID4ofOs.html"
    },
    {
        "offer_id": "998089494",
        "title": "Nowe 3- pokojowe mieszkanie taras/ gara\u017c/winda",
        "price": "699 900 z\u0142",
        "location": "Wroc\u0142aw, Psie Pole",
        "date": "24 kwietnia 2025",
        "ref": "https://www.otodom.pl/pl/oferta/nowe-3-pokojowe-mieszkanie-taras-garaz-winda-ID4v6kk.html"
    },
    {
        "offer_id": "1000350948",
        "title": "Przestronna Kawalerka przy Parku \u017berniki",
        "price": "430 122 z\u0142",
        "location": "Wroc\u0142aw",
        "date": "06 maja 2025",
        "ref": "https://www.otodom.pl/pl/oferta/przestronna-kawalerka-przy-parku-zerniki-ID4vfGO.html"
    },
    {
        "offer_id": "915284921",
        "title": "Pod Ole\u015bnic\u0105/Super cena i lokalizacja/balkon/kom.l",
        "price": "377 456 z\u0142",
        "location": "Bierut\u00f3w",
        "date": "25 kwietnia 2025",
        "ref": "https://www.otodom.pl/pl/oferta/pod-olesnica-super-cena-i-lokalizacja-balkon-kom-l-ID4qmcu.html"
    },
    {
        "offer_id": "891922307",
        "title": "2 pokojowe z balkonem! Mi\u0119kinia",
        "price": "435 000 z\u0142",
        "location": "Mi\u0119kinia",
        "date": "04 maja 2025",
        "ref": "https://www.otodom.pl/pl/oferta/2-pokojowe-z-balkonem-miekinia-ID4oLvF.html"
    },
    {
        "offer_id": "999088942",
        "title": "GOTOWE 2-pokojowe mieszkanie 43,54 m2 | D2/P2/1",
        "price": "404 922 z\u0142",
        "location": "O\u0142awa",
        "date": "29 kwietnia 2025",
        "ref": "https://www.otodom.pl/pl/oferta/gotowe-2-pokojowe-mieszkanie-43-54-m2-d2-p2-1-ID4rUED.html"
    },
    {
        "offer_id": "999570628",
        "title": "4 pokoje|Stadion|Park|Komunikacja miejska|",
        "price": "970 202 z\u0142",
        "location": "Wroc\u0142aw",
        "date": "02 maja 2025",
        "ref": "https://www.otodom.pl/pl/oferta/4-pokoje-stadion-park-komunikacja-miejska-ID4tjZK.html"
    },
    {
        "offer_id": "1003135806",
        "title": "O\u0142awa Jod\u0142owa / nowy etap / 2 miejsca parkingowe",
        "price": "395 000 z\u0142",
        "location": "O\u0142awa",
        "date": "18 maja 2025",
        "ref": "https://www.otodom.pl/pl/oferta/olawa-jodlowa-nowy-etap-2-miejsca-parkingowe-ID4vrcQ.html"
    },
    {
        "offer_id": "953676573",
        "title": "Wyko\u0144czona dwupoziomowa kawalerka 43m2, centrum!",
        "price": "569 000 z\u0142",
        "location": "Wroc\u0142aw, Psie Pole",
        "date": "06 maja 2025",
        "ref": "https://www.otodom.pl/pl/oferta/wykonczona-dwupoziomowa-kawalerka-43m2-centrum-ID4t4Gl.html"
    },
    {
        "offer_id": "948750372",
        "title": "Osiedle Ko\u015bciuszki Brzeg --\" najlepsza lokalizacja w Brzegu \" --",
        "price": "432 000 z\u0142",
        "location": "Brzeg",
        "date": "08 maja 2025",
        "ref": "https://www.otodom.pl/pl/oferta/osiedle-kosciuszki-brzeg-najlepsza-lokalizacja-w-brzegu-ID4sJvM.html"
    },
    {
        "offer_id": "996663695",
        "title": "Przestronne dwupoziomowe 78m2 z balkonem i tarasem",
        "price": "836 446 z\u0142",
        "location": "Wroc\u0142aw, Fabryczna",
        "date": "16 kwietnia 2025",
        "ref": "https://www.otodom.pl/pl/oferta/przestronne-dwupoziomowe-78m2-z-balkonem-i-tarasem-ID4wZZU.html"
    },
    {
        "offer_id": "1000791408",
        "title": "Grabiszy\u0144ska+ | B.8.M.01",
        "price": "1 268 760 z\u0142",
        "location": "Wroc\u0142aw, Fabryczna",
        "date": "08 maja 2025",
        "ref": "https://www.otodom.pl/pl/oferta/grabiszynska-b-8-m-01-ID4tEME.html"
    },
    {
        "offer_id": "999674596",
        "title": "Dwa pi\u0119tra | Dwa Balkony | 3 Pokoje",
        "price": "890 000 z\u0142",
        "location": "Wroc\u0142aw, Krzyki",
        "date": "03 maja 2025",
        "ref": "https://www.otodom.pl/pl/oferta/dwa-pietra-dwa-balkony-3-pokoje-ID4wKTM.html"
    },
    {
        "offer_id": "990575621",
        "title": "2 pokoje, du\u017cy balkon. ul. Kajdasza- Bezpo\u015brednio",
        "price": "465 000 z\u0142",
        "location": "Wroc\u0142aw, Krzyki",
        "date": "03 maja 2025",
        "ref": "https://www.olx.pl/d/oferta/2-pokoje-duzy-balkon-ul-kajdasza-bezposrednio-CID3-ID152lY9.html"
    },
    {
        "offer_id": "847742774",
        "title": "NOWE BLOKI ul. Korczaka 15A wysoki parter",
        "price": "416 232 z\u0142",
        "location": "Dzier\u017coni\u00f3w",
        "date": "07 maja 2025",
        "ref": "https://www.otodom.pl/pl/oferta/nowe-bloki-ul-korczaka-15a-wysoki-parter-ID4meUz.html"
    },
    {
        "offer_id": "1000731141",
        "title": "Od dewelopera! Centrum miasta_kawalerka z balkonem!",
        "price": "419 999 z\u0142",
        "location": "Wroc\u0142aw, Fabryczna",
        "date": "08 maja 2025",
        "ref": "https://www.otodom.pl/pl/oferta/od-dewelopera-centrum-miasta-kawalerka-z-balkonem-ID4vhCC.html"
    },
    {
        "offer_id": "989148795",
        "title": "NOWA PABIANICKA |2POK| opcja wyko\u0144czenia pod klucz",
        "price": "649 000 z\u0142",
        "location": "Wroc\u0142aw, Krzyki",
        "date": "01 maja 2025",
        "ref": "https://www.otodom.pl/pl/oferta/nowa-pabianicka-2pok-opcja-wykonczenia-pod-klucz-ID4wmZi.html"
    },
    {
        "offer_id": "1003219412",
        "title": "GOTOWE 2-pokojowe mieszkanie 37,98 m2 | D2/P1/3",
        "price": "353 214 z\u0142",
        "location": "O\u0142awa",
        "date": "19 maja 2025",
        "ref": "https://www.otodom.pl/pl/oferta/gotowe-2-pokojowe-mieszkanie-37-98-m2-d2-p1-3-ID4rUEx.html"
    },
    {
        "offer_id": "995899825",
        "title": "Ogrody Zawisz\u00f3w II  | mieszkanie 3-pok. | B-002",
        "price": "711 060 z\u0142",
        "location": "\u015awidnica",
        "date": "12 maja 2025",
        "ref": "https://www.otodom.pl/pl/oferta/ogrody-zawiszow-ii-mieszkanie-3-pok-b-002-ID4sr6o.html"
    },
    {
        "offer_id": "999566662",
        "title": "2 pokoje|Zielona okolica|Galeria Handlowa|",
        "price": "486 080 z\u0142",
        "location": "Wroc\u0142aw",
        "date": "02 maja 2025",
        "ref": "https://www.otodom.pl/pl/oferta/2-pokoje-zielona-okolica-galeria-handlowa-ID4sfLx.html"
    },
    {
        "offer_id": "999997727",
        "title": "Jagodno, ul.Kajdasza, 2 pokoje, du\u017cy balkon, 37,6 m2, bezpo\u015brednio",
        "price": "479 000 z\u0142",
        "location": "Wroc\u0142aw, Krzyki",
        "date": "04 maja 2025",
        "ref": "https://www.otodom.pl/pl/oferta/jagodno-ul-kajdasza-2-pokoje-duzy-balkon-37-6-m2-bezposrednio-ID4vdO4.html"
    },
    {
        "offer_id": "749193876",
        "title": "Nowe bloki ul. Korczaka 15 E, parter",
        "price": "362 160 z\u0142",
        "location": "Dzier\u017coni\u00f3w",
        "date": "12 maja 2025",
        "ref": "https://www.otodom.pl/pl/oferta/nowe-bloki-ul-korczaka-15-e-parter-ID4gcsf.html"
    },
    {
        "offer_id": "1003456674",
        "title": "ZAKO\u0143CZONA BUDOWA - Gotowe mieszkanie 3-pokojowe",
        "price": "701 341 z\u0142",
        "location": "Wroc\u0142aw, Krzyki",
        "date": "dzisiaj o 15:07",
        "ref": "https://www.olx.pl/d/oferta/zakonczona-budowa-gotowe-mieszkanie-3-pokojowe-CID3-ID15UoW4.html"
    },
    {
        "offer_id": "1003035946",
        "title": "Kopernika 16 | mieszkanie 3-pok. | F04",
        "price": "585 877 z\u0142",
        "location": "Ole\u015bnica",
        "date": "18 maja 2025",
        "ref": "https://www.otodom.pl/pl/oferta/kopernika-16-mieszkanie-3-pok-f04-ID4vbrV.html"
    },
    {
        "offer_id": "975836194",
        "title": "3 pokoje z balkonem na O\u0142taszynie",
        "price": "598 000 z\u0142",
        "location": "Wroc\u0142aw, Krzyki",
        "date": "31 marca 2025",
        "ref": "https://www.otodom.pl/pl/oferta/3-pokoje-z-balkonem-na-oltaszynie-ID4uu7d.html"
    },
    {
        "offer_id": "830358890",
        "title": "Mieszkanie dwupoziomowe 102 m2 - gotowe z aktem",
        "price": "877 403,30 z\u0142",
        "location": "Wroc\u0142aw",
        "date": "22 kwietnia 2025",
        "ref": "https://www.otodom.pl/pl/oferta/mieszkanie-dwupoziomowe-102-m2-gotowe-z-aktem-ID4lbpY.html"
    },
    {
        "offer_id": "1000113037",
        "title": "Lipa Piotrowska | mieszkanie C/K2/8",
        "price": "586 915,50 z\u0142",
        "location": "Wroc\u0142aw",
        "date": "05 maja 2025",
        "ref": "https://www.otodom.pl/pl/oferta/lipa-piotrowska-mieszkanie-c-k2-8-ID4so38.html"
    },
    {
        "offer_id": "999566669",
        "title": "Gotowe 4 pok w atrakcyjnej cenie Radwanice",
        "price": "719 287 z\u0142",
        "location": "Wroc\u0142aw, Krzyki",
        "date": "02 maja 2025",
        "ref": "https://www.otodom.pl/pl/oferta/gotowe-4-pok-w-atrakcyjnej-cenie-radwanice-ID4rAVd.html"
    },
    {
        "offer_id": "1000113039",
        "title": "Lipa Piotrowska | mieszkanie C/K2/3",
        "price": "470 032 z\u0142",
        "location": "Wroc\u0142aw",
        "date": "05 maja 2025",
        "ref": "https://www.otodom.pl/pl/oferta/lipa-piotrowska-mieszkanie-c-k2-3-ID4so3b.html"
    },
    {
        "offer_id": "840206697",
        "title": "Przysta\u0144 Kr\u00f3lewiecka III | mieszkanie K1/23",
        "price": "724 259 z\u0142",
        "location": "Wroc\u0142aw, Fabryczna",
        "date": "25 kwietnia 2025",
        "ref": "https://www.otodom.pl/pl/oferta/przystan-krolewiecka-iii-mieszkanie-k1-23-ID4kGjA.html"
    },
    {
        "offer_id": "995899813",
        "title": "Ogrody Zawisz\u00f3w II  | mieszkanie 3-pok. | B-210",
        "price": "734 762 z\u0142",
        "location": "\u015awidnica",
        "date": "12 maja 2025",
        "ref": "https://www.otodom.pl/pl/oferta/ogrody-zawiszow-ii-mieszkanie-3-pok-b-210-ID4sr6s.html"
    },
    {
        "offer_id": "972179724",
        "title": "Okazja! 33m2 blisko lotniska - idealne na wynajem",
        "price": "139 000 z\u0142",
        "location": "Wroc\u0142aw, Fabryczna",
        "date": "dzisiaj o 17:06",
        "ref": "https://www.otodom.pl/pl/oferta/okazja-33m2-blisko-lotniska-idealne-na-wynajem-ID4u7Dl.html"
    },
    {
        "offer_id": "973226170",
        "title": "2 pokoje / Dobry dojazd do centrum",
        "price": "372 200 z\u0142",
        "location": "Wroc\u0142aw, Krzyki",
        "date": "27 kwietnia 2025",
        "ref": "https://www.otodom.pl/pl/oferta/2-pokoje-dobry-dojazd-do-centrum-ID4uegB.html"
    },
    {
        "offer_id": "882108677",
        "title": "70m\u00b2+OGR\u00d3D 61m\u00b2+m.postojowe -KAMERALNE-C",
        "price": "580 000 z\u0142",
        "location": "Lutynia",
        "date": "23 kwietnia 2025",
        "ref": "https://www.otodom.pl/pl/oferta/70m-ogrod-61m-m-postojowe-kameralne-c-ID4oa1u.html"
    },
    {
        "offer_id": "1001974764",
        "title": "Mieszkanie osiedle m\u0142odych ( Parter ) 2 pokoje",
        "price": "382 000 z\u0142\ndo negocjacji",
        "location": "\u015awidnica",
        "date": "13 maja 2025",
        "ref": "https://www.olx.pl/d/oferta/mieszkanie-osiedle-mlodych-parter-2-pokoje-CID3-ID15Obpi.html?reason=extended_search_extended_distance"
    },
    {
        "offer_id": "951309020",
        "title": "Nowe, du\u017ce mieszkanie w Strzelinie LE\u015aNA 7",
        "price": "484 382 z\u0142",
        "location": "Strzelin",
        "date": "20 kwietnia 2025",
        "ref": "https://www.olx.pl/d/oferta/nowe-duze-mieszkanie-w-strzelinie-lesna-7-CID3-ID12nAWS.html?reason=extended_search_extended_distance"
    },
    {
        "offer_id": "1000403932",
        "title": "Ogr\u00f3d Zimowy | Zielone Tereny | Mega Okazja |0%PCC",
        "price": "726 000 z\u0142",
        "location": "Wroc\u0142aw, Krzyki",
        "date": "06 maja 2025",
        "ref": "https://www.otodom.pl/pl/oferta/ogrod-zimowy-zielone-tereny-mega-okazja-0-pcc-ID4vfZc.html"
    },
    {
        "offer_id": "761294564",
        "title": "111m\u00b2+balkon+m.postojowe -dwupoziomowe-KAMERALNE-C",
        "price": "620 000 z\u0142",
        "location": "Lutynia",
        "date": "23 kwietnia 2025",
        "ref": "https://www.otodom.pl/pl/oferta/111m-balkon-m-postojowe-dwupoziomowe-kameralne-c-ID4h4rb.html"
    },
    {
        "offer_id": "882108811",
        "title": "70m\u00b2+OGR\u00d3D 61m\u00b2+m.postojowe -KAMERALNE-C",
        "price": "580 000 z\u0142",
        "location": "Lutynia",
        "date": "23 kwietnia 2025",
        "ref": "https://www.otodom.pl/pl/oferta/70m-ogrod-61m-m-postojowe-kameralne-c-ID4o9ZK.html"
    },
    {
        "offer_id": "936250009",
        "title": "GOTOWE 3-pokojowe mieszkanie 53,92 m2 | D2/P4/5",
        "price": "496 064 z\u0142",
        "location": "O\u0142awa",
        "date": "19 maja 2025",
        "ref": "https://www.otodom.pl/pl/oferta/gotowe-3-pokojowe-mieszkanie-53-92-m2-d2-p4-5-ID4rUF1.html"
    },
    {
        "offer_id": "1003008641",
        "title": "Przestronny dwupoziopowy apartament z tarasem.",
        "price": "790 884 z\u0142",
        "location": "Wroc\u0142aw, Krzyki",
        "date": "18 maja 2025",
        "ref": "https://www.otodom.pl/pl/oferta/przestronny-dwupoziopowy-apartament-z-tarasem-ID4tah3.html"
    },
    {
        "offer_id": "884662871",
        "title": "70m\u00b2+OGR\u00d3D 61m\u00b2+1 m.parking+kom\u00f3rka-KAMERALNE",
        "price": "580 000 z\u0142",
        "location": "Lutynia",
        "date": "25 kwietnia 2025",
        "ref": "https://www.otodom.pl/pl/oferta/70m-ogrod-61m-1-m-parking-komorka-kameralne-ID4ofO0.html"
    },
    {
        "offer_id": "1003035947",
        "title": "Kopernika 16 | mieszkanie 4-pok. | E08",
        "price": "917 322 z\u0142",
        "location": "Ole\u015bnica",
        "date": "18 maja 2025",
        "ref": "https://www.otodom.pl/pl/oferta/kopernika-16-mieszkanie-4-pok-e08-ID4vbrS.html"
    },
    {
        "offer_id": "999243276",
        "title": "Dwupoziomowy apartament z balkonem i tarasem",
        "price": "599 896 z\u0142",
        "location": "Brzeg",
        "date": "30 kwietnia 2025",
        "ref": "https://www.otodom.pl/pl/oferta/dwupoziomowy-apartament-z-balkonem-i-tarasem-ID4v2cX.html"
    },
    {
        "offer_id": "959866612",
        "title": "GOTOWE 2-pokojowe mieszkanie 41,25 m2 | D2/P4/2",
        "price": "383 625 z\u0142",
        "location": "O\u0142awa",
        "date": "19 maja 2025",
        "ref": "https://www.otodom.pl/pl/oferta/gotowe-2-pokojowe-mieszkanie-41-25-m2-d2-p4-2-ID4rUEW.html"
    },
    {
        "offer_id": "981268237",
        "title": "Ogrody Zawisz\u00f3w II  | mieszkanie 3-pok. | A-003",
        "price": "712 425 z\u0142",
        "location": "\u015awidnica",
        "date": "12 maja 2025",
        "ref": "https://www.otodom.pl/pl/oferta/ogrody-zawiszow-ii-mieszkanie-3-pok-a-003-ID4sr6r.html"
    },
    {
        "offer_id": "1000815610",
        "title": "Apartamenty przy Parku Szczytnickim | 2-pok mieszkanie z ogr\u00f3dkiem",
        "price": "909 870,75 z\u0142",
        "location": "Wroc\u0142aw, \u015ar\u00f3dmie\u015bcie",
        "date": "08 maja 2025",
        "ref": "https://www.otodom.pl/pl/oferta/apartamenty-przy-parku-szczytnickim-2-pok-mieszkanie-z-ogrodkiem-ID4vijY.html"
    },
    {
        "offer_id": "998004276",
        "title": "Mieszkanie 2 pok. w centrum Wroc\u0142awia - Szczepin/Stare Miasto-Okazja!",
        "price": "525 000 z\u0142",
        "location": "Wroc\u0142aw, Stare Miasto",
        "date": "24 kwietnia 2025",
        "ref": "https://www.otodom.pl/pl/oferta/mieszkanie-2-pok-w-centrum-wroclawia-szczepin-stare-miasto-okazja-ID4v5E9.html"
    },
    {
        "offer_id": "974225178",
        "title": "Mieszkania od pow. 38,36 m2",
        "price": "364 420 z\u0142",
        "location": "Trzebnica",
        "date": "10 kwietnia 2025",
        "ref": "https://www.otodom.pl/pl/oferta/mieszkania-od-pow-38-36-m2-ID4uhV2.html"
    }
]